vidlink/__init__.py
vidlink/vidlink.py
vidlink-0.1.6.dist-info/METADATA
vidlink-0.1.6.dist-info/WHEEL
vidlink-0.1.6.dist-info/RECORD
